MANIFEST.in
README.md
setup.cfg
setup.py
HyBayes/Bayes_factor_analysis.py
HyBayes/__init__.py
HyBayes/__main__.py
HyBayes/config_template.ini
HyBayes/experiment.py
HyBayes/make_configs.py
HyBayes/make_data.py
HyBayes/utils.py
HyBayes/visualization.py
HyBayes/models/__init__.py
HyBayes/models/beta_bern_model.py
HyBayes/models/beta_binomial_model.py
HyBayes/models/contingency_model.py
HyBayes/models/count_model.py
HyBayes/models/inv_model.py
HyBayes/models/metric_model.py
HyBayes/models/ordinal_model.py
hybayes.egg-info/PKG-INFO
hybayes.egg-info/SOURCES.txt
hybayes.egg-info/dependency_links.txt
hybayes.egg-info/not-zip-safe
hybayes.egg-info/requires.txt
hybayes.egg-info/top_level.txt