Metadata-Version: 2.1
Name: hybayes
Version: 0.0.2
Summary: Bayesian Assessment of Hypotheses
Home-page: https://github.com/allenai/HyBayes
Author: Erfan Sadeqi Azer, Daniel Khashabi
Author-email: esamath@gmail.com
License: BY-NC-SA
Download-URL: https://github.com/allenai/HyBayes/archive/0.0.2.tar.gz
Keywords: Bayesian Statistics,two groups test,Hypothesis Testing,Bayes Factor,NLP,natural language processing,
Platform: UNKNOWN
Classifier: Development Status :: 3 - Alpha
Classifier: Intended Audience :: Science/Research
Classifier: Operating System :: OS Independent
Classifier: Programming Language :: Python :: 3
Classifier: Programming Language :: Python :: 3.4
Classifier: Programming Language :: Python :: 3.5
Classifier: Programming Language :: Python :: 3.6
Classifier: Topic :: Scientific/Engineering
